odoo9_addon_hr_payroll_report-9.0.1.0.0.99.dev5-py2.7-nspkg.pth
odoo9_addon_hr_payroll_report-9.0.1.0.0.99.dev5.dist-info/METADATA
odoo9_addon_hr_payroll_report-9.0.1.0.0.99.dev5.dist-info/RECORD
odoo9_addon_hr_payroll_report-9.0.1.0.0.99.dev5.dist-info/WHEEL
odoo9_addon_hr_payroll_report-9.0.1.0.0.99.dev5.dist-info/namespace_packages.txt
odoo9_addon_hr_payroll_report-9.0.1.0.0.99.dev5.dist-info/top_level.txt
odoo_addons/hr_payroll_report/README.rst
odoo_addons/hr_payroll_report/__init__.py
odoo_addons/hr_payroll_report/__openerp__.py
odoo_addons/hr_payroll_report/i18n/de.po
odoo_addons/hr_payroll_report/i18n/hr_payroll_report.pot
odoo_addons/hr_payroll_report/models/__init__.py
odoo_addons/hr_payroll_report/models/hr_payslip_line.py
odoo_addons/hr_payroll_report/static/description/icon.png
odoo_addons/hr_payroll_report/views/hr_payroll_report_menu.xml
odoo_addons/hr_payroll_report/views/hr_payslip_line_view.xml
