Metadata-Version: 2.1
Name: odoo9-addon-hr-payroll-report
Version: 9.0.1.0.0.99.dev5
Summary: Analyze your payroll with the Payslip Lines BI report
Home-page: https://www.elico-corp.com/
Author: Elico Corp, Odoo Community Association (OCA)
Author-email: support@odoo-community.org
License: AGPL-3
Platform: UNKNOWN
Classifier: Programming Language :: Python
Classifier: Framework :: Odoo
Classifier: License :: OSI Approved :: GNU Affero General Public License v3
Requires-Python: ~=2.7
Requires-Dist: odoo (<9.1a,>=9.0a)
